{
  "timestamp": "2025-11-27T16:46:55.490422",
  "components_run": [
    2,
    6
  ],
  "results": {
    "component_2": {
      "status": "completed",
      "output_dir": "results\\optimization\\thresholds"
    },
    "component_6": {
      "status": "configs_generated",
      "total_configs": 36
    }
  },
  "expected_improvements": {
    "accuracy": "+10-15% (53.76% -> 63-68%)",
    "macro_f1": "+0.08-0.12 (0.476 -> 0.55-0.60)",
    "fear_f1": "+0.17-0.23 (0.275 -> 0.45-0.50)",
    "disgust_f1": "+0.22-0.27 (0.281 -> 0.50-0.55)"
  }
}